atlasui/__init__.py
atlasui/config.py
atlasui/configure.py
atlasui/manage.py
atlasui/operations_manager.py
atlasui/server.py
atlasui/session_manager.py
atlasui/api/__init__.py
atlasui/api/alerts.py
atlasui/api/backups.py
atlasui/api/clusters.py
atlasui/api/databases.py
atlasui/api/operations.py
atlasui/api/organizations.py
atlasui/api/pages.py
atlasui/api/projects.py
atlasui/api/server.py
atlasui/api/setup.py
atlasui/api/users.py
atlasui/cli/__init__.py
atlasui/cli/alerts.py
atlasui/cli/backups.py
atlasui/cli/clusters.py
atlasui/cli/main.py
atlasui/cli/projects.py
atlasui/client/__init__.py
atlasui/client/auth.py
atlasui/client/base.py
atlasui/client/service_account.py
atlasui/static/favicon.svg
atlasui/static/css/style.css
atlasui/static/js/app.js
atlasui/static/js/operations-queue.js
atlasui/templates/all_clusters.html
atlasui/templates/base.html
atlasui/templates/clusters.html
atlasui/templates/dashboard.html
atlasui/templates/databases.html
atlasui/templates/organizations.html
atlasui/templates/projects.html
atlasui/templates/setup.html
atlasui/templates/users.html
atlasui-0.3.4.dist-info/licenses/LICENSE
atlasui-0.3.4.dist-info/METADATA
atlasui-0.3.4.dist-info/WHEEL
atlasui-0.3.4.dist-info/entry_points.txt
atlasui-0.3.4.dist-info/top_level.txt
atlasui-0.3.4.dist-info/RECORD
