Metadata-Version: 2.4
Name: atlasui
Version: 0.3.4
Summary: User Interface for MongoDB Atlas - Web UI and CLI tool
Author: Joe Drumgoole
Requires-Python: >=3.10
License-File: LICENSE
Requires-Dist: fastapi>=0.115.0
Requires-Dist: uvicorn[standard]>=0.32.0
Requires-Dist: pydantic>=2.9.0
Requires-Dist: pydantic-settings>=2.6.0
Requires-Dist: httpx>=0.27.0
Requires-Dist: typer>=0.12.0
Requires-Dist: rich>=13.9.0
Requires-Dist: python-multipart>=0.0.12
Requires-Dist: jinja2>=3.1.4
Requires-Dist: pyyaml>=6.0.2
Requires-Dist: pymongo>=4.10.0
Requires-Dist: tomli>=2.0.0; python_version < "3.11"
Requires-Dist: slowapi>=0.1.9
Requires-Dist: shot-scraper>=1.8
Provides-Extra: dev
Requires-Dist: pytest>=8.3.0; extra == "dev"
Requires-Dist: pytest-asyncio>=0.24.0; extra == "dev"
Requires-Dist: pytest-cov>=6.0.0; extra == "dev"
Requires-Dist: pytest-xdist>=3.6.0; extra == "dev"
Requires-Dist: black>=24.10.0; extra == "dev"
Requires-Dist: ruff>=0.7.0; extra == "dev"
Requires-Dist: mypy>=1.13.0; extra == "dev"
Requires-Dist: invoke>=2.2.0; extra == "dev"
Provides-Extra: docs
Requires-Dist: sphinx>=8.1.0; extra == "docs"
Requires-Dist: sphinx-rtd-theme>=3.0.0; extra == "docs"
Requires-Dist: sphinx-autodoc-typehints>=2.5.0; extra == "docs"
Requires-Dist: myst-parser>=4.0.0; extra == "docs"
Dynamic: license-file
